LICENSE
README.md
setup.py
pymortafix/__init__.py
pymortafix/_getchar.py
pymortafix/telegram.py
pymortafix/utils.py
pymortafix.egg-info/PKG-INFO
pymortafix.egg-info/SOURCES.txt
pymortafix.egg-info/dependency_links.txt
pymortafix.egg-info/requires.txt
pymortafix.egg-info/top_level.txt