Metadata-Version: 2.1
Name: pymortafix
Version: 0.2.3
Summary: A python module to collect some usefull stuff
Home-page: https://github.com/mortafix/PyMortafix
Author: Moris Doratiotto
Author-email: moris.doratiotto@gmail.com
Keywords: telegram,bot,utils
Classifier: Programming Language :: Python :: 3.8
Classifier: License :: OSI Approved :: MIT License
Classifier: Operating System :: OS Independent
Classifier: Development Status :: 3 - Alpha
Classifier: Intended Audience :: Developers
Requires-Python: >=3.8
License-File: LICENSE
